calculator/__init__.py
calculator/addition.py
calculator/division.py
calculator/multiplication.py
calculator/subtraction.py
tests/__init__.py
tests/test_calculator.py
mohan_basic_calculator-0.1.0.dist-info/License.txt
mohan_basic_calculator-0.1.0.dist-info/METADATA
mohan_basic_calculator-0.1.0.dist-info/WHEEL
mohan_basic_calculator-0.1.0.dist-info/top_level.txt
mohan_basic_calculator-0.1.0.dist-info/RECORD
