Metadata-Version: 2.1
Name: mohan-basic-calculator
Version: 0.1.0
Summary: Simple Calculator App in Python
Home-page: UNKNOWN
Author: mohan raja
Author-email: mohanraja2327@gmail.com
License: UNKNOWN
Platform: UNKNOWN
Classifier: Programming Language :: Python :: 3
Classifier: License :: OSI Approved :: MIT License
Classifier: Operating System :: OS Independent
License-File: License.txt
